godfather_cli/__init__.py
godfather_cli/auth.py
godfather_cli/cli.py
godfather_cli/pod_manager.py
godfather_cli/ssh_connector.py
godfather_cli/update_checker.py
godfather_cli-1.0.10.dist-info/METADATA
godfather_cli-1.0.10.dist-info/WHEEL
godfather_cli-1.0.10.dist-info/entry_points.txt
godfather_cli-1.0.10.dist-info/top_level.txt
godfather_cli-1.0.10.dist-info/RECORD
