Metadata-Version: 2.4
Name: godfather-cli
Version: 1.0.10
Summary: AI Society Godfather CLI - RunPod Environment Manager
Author-email: AI Society ASU <theaisocietyasu@gmail.com>
License: MIT
Project-URL: Homepage, https://github.com/theaisocietyasu/godfather
Project-URL: Repository, https://github.com/theaisocietyasu/godfather
Project-URL: Issues, https://github.com/theaisocietyasu/godfather/issues
Classifier: Development Status :: 4 - Beta
Classifier: Intended Audience :: Developers
Classifier: License :: OSI Approved :: MIT License
Classifier: Programming Language :: Python :: 3
Classifier: Programming Language :: Python :: 3.7
Classifier: Programming Language :: Python :: 3.8
Classifier: Programming Language :: Python :: 3.9
Classifier: Programming Language :: Python :: 3.10
Classifier: Programming Language :: Python :: 3.11
Requires-Python: >=3.7
Requires-Dist: requests>=2.25.0
Requires-Dist: rich>=13.0.0
Requires-Dist: packaging>=20.0
